torchhook/__init__.py
torchhook/hookmanager.py
torchhook/utils.py
TorchHook-0.2.7.dist-info/LICENSE
TorchHook-0.2.7.dist-info/METADATA
TorchHook-0.2.7.dist-info/WHEEL
TorchHook-0.2.7.dist-info/top_level.txt
TorchHook-0.2.7.dist-info/RECORD
