Metadata-Version: 2.1
Name: TorchHook
Version: 0.2.7
Summary: TouchHook: A PyTorch hook management library
Home-page: https://github.com/zzaiyan/TorchHook
Author: Zaiyan Zhang
Author-email: 1@zzaiyan.com
Classifier: Programming Language :: Python :: 3
Classifier: License :: OSI Approved :: MIT License
Classifier: Operating System :: OS Independent
Requires-Python: >=3.6
License-File: LICENSE
Requires-Dist: torch>=1.0.0
